README.rst
setup.cfg
setup.py
android_utils/CurlDownloadHelper.py
android_utils/__init__.py
android_utils/apkinfo.py
android_utils.egg-info/PKG-INFO
android_utils.egg-info/SOURCES.txt
android_utils.egg-info/dependency_links.txt
android_utils.egg-info/top_level.txt
android_utils.egg-info/zip-safe