Metadata-Version: 1.1
Name: android-utils
Version: 1.1.6
Summary: xinge Push API for Python(http://xg.qq.com).
Home-page: https://github.com/xingePush/xinge-api-python
Author: yang
Author-email: 1020211152@qq.com
License: MIT
Keywords: android,Android,androidutils,android_utils
Platform: any
Classifier: License :: OSI Approved :: MIT License
Classifier: Programming Language :: Python
Classifier: Intended Audience :: Developers
Classifier: Operating System :: OS Independent
